<?xml version="1.0" encoding="UTF-8"?>
<LanguageData>
  
  <!-- EN: animalist -->
  <Animalist.label>анималист</Animalist.label>
  
  <!-- EN: Buddhist -->
  <Buddhist.label>Буддийский</Buddhist.label>
  
  <!-- EN: Christian -->
  <Christian.label>Христианский</Christian.label>
  
  <!-- EN: Hindu -->
  <Hindu.label>Индуистский</Hindu.label>
  
  <!-- EN: Islamic -->
  <Islamic.label>Исламский</Islamic.label>
  
  <!-- EN: morbid -->
  <Morbid.label>мрачный</Morbid.label>
  
  <!-- EN: rustic -->
  <Rustic.label>простой</Rustic.label>
  
  <!-- EN: spikecore -->
  <Spikecore.label>колючий</Spikecore.label>
  
  <!-- EN: techist -->
  <Techist.label>техно</Techist.label>
  
  <!-- EN: totemic -->
  <Totemic.label>тотемный</Totemic.label>
  
</LanguageData>